pyzab/__init__.py
pyzab/pz.py
pyzab-0.1.4.dist-info/METADATA
pyzab-0.1.4.dist-info/WHEEL
pyzab-0.1.4.dist-info/top_level.txt
pyzab-0.1.4.dist-info/RECORD
